{
  "url": "https://sjc.com.vn/GoldPrice/Services/PriceService.ashx",
  "status": 200,
  "text": "{\"success\":true,\"data\":[{\"Id\":0,\"TypeName\":\"Vàng SJC 1L, 10L, 1KG\",\"BranchName\":\"Hồ Chí Minh\",\"Buy\":\"43,550\",\"BuyValue\":43550000.0000,\"Sell\":\"43,950\",\"SellValue\":43950000.0000,\"BuyDiffer\":null,\"BuyDifferValue\":0,\"SellDiffer\":null,\"SellDifferValue\":0,\"GroupDate\":\"\\/Date(1580835600000)\\/\"},{\"Id\":0,\"TypeName\":\"Vàng SJC 1L, 10L, 1KG\",\"BranchName\":\"Hồ Chí Minh\",\"Buy\":\"43,250\",\"BuyValue\":43250000.0000,\"Sell\":\"43,750\",\"SellValue\":43750000.0000,\"BuyDiffer\":null,\"BuyDifferValue\":0,\"SellDiffer\":null,\"SellDifferValue\":0,\"GroupDate\":\"\\/Date(1580841170000)\\/\"},{\"Id\":0,\"TypeName\":\"Vàng SJC 1L, 10L, 1KG\",\"BranchName\":\"Hồ Chí Minh\",\"Buy\":\"43,300\",\"BuyValue\":43300000.0000,\"Sell\":\"43,800\",\"SellValue\":43800000.0000,\"BuyDiffer\":null,\"BuyDifferValue\":0,\"SellDiffer\":null,\"SellDifferValue\":0,\"GroupDate\":\"\\/Date(1580848893000)\\/\"},{\"Id\":0,\"TypeName\":\"Vàng SJC 1L, 10L, 1KG\",\"BranchName\":\"Hồ Chí Minh\",\"Buy\":\"43,350\",\"BuyValue\":43350000.0000,\"Sell\":\"43,800\",\"SellValue\":43800000.0000,\"BuyDiffer\":null,\"BuyDifferValue\":0,\"SellDiffer\":null,\"SellDifferValue\":0,\"GroupDate\":\"\\/Date(1580849146000)\\/\"},{\"Id\":0,\"TypeName\":\"Vàng SJC 1L, 10L, 1KG\",\"BranchName\":\"Hồ Chí Minh\",\"Buy\":\"43,400\",\"BuyValue\":43400000.0000,\"Sell\":\"43,850\",\"SellValue\":43850000.0000,\"BuyDiffer\":null,\"BuyDifferValue\":0,\"SellDiffer\":null,\"SellDifferValue\":0,\"GroupDate\":\"\\/Date(1580858851000)\\/\"},{\"Id\":0,\"TypeName\":\"Vàng SJC 1L, 10L, 1KG\",\"BranchName\":\"Hồ Chí Minh\",\"Buy\":\"43,500\",\"BuyValue\":43500000.0000,\"Sell\":\"43,950\",\"SellValue\":43950000.0000,\"BuyDiffer\":null,\"BuyDifferValue\":0,\"SellDiffer\":null,\"SellDifferValue\":0,\"GroupDate\":\"\\/Date(1580860150000)\\/\"},{\"Id\":0,\"TypeName\":\"Vàng SJC 1L, 10L, 1KG\",\"BranchName\":\"Hồ Chí Minh\",\"Buy\":\"43,450\",\"BuyValue\":43450000.0000,\"Sell\":\"43,900\",\"SellValue\":43900000.0000,\"BuyDiffer\":null,\"BuyDifferValue\":0,\"SellDiffer\":null,\"SellDifferValue\":0,\"GroupDate\":\"\\/Date(1580860314000)\\/\"},{\"Id\":0,\"TypeName\":\"Vàng SJC 1L, 10L, 1KG\",\"BranchName\":\"Hồ Chí Minh\",\"Buy\":\"43,500\",\"BuyValue\":43500000.0000,\"Sell\":\"43,950\",\"SellValue\":43950000.0000,\"BuyDiffer\":null,\"BuyDifferValue\":0,\"SellDiffer\":null,\"SellDifferValue\":0,\"GroupDate\":\"\\/Date(1580861989000)\\/\"},{\"Id\":0,\"TypeName\":\"Vàng SJC 1L, 10L, 1KG\",\"BranchName\":\"Hồ Chí Minh\",\"Buy\":\"43,450\",\"BuyValue\":43450000.0000,\"Sell\":\"43,900\",\"SellValue\":43900000.0000,\"BuyDiffer\":null,\"BuyDifferValue\":0,\"SellDiffer\":null,\"SellDifferValue\":0,\"GroupDate\":\"\\/Date(1580867297000)\\/\"}]}",
  "raw_payload_hash": "f86e2c581d428c98c074becbbd9210d6333619ce4661b6b238e0fb42b1196662",
  "from_cache": false
}