{
  "url": "https://sjc.com.vn/GoldPrice/Services/PriceService.ashx",
  "status": 200,
  "text": "{\"success\":true,\"data\":[{\"Id\":0,\"TypeName\":\"Vàng SJC 1L, 10L, 1KG\",\"BranchName\":\"Hồ Chí Minh\",\"Buy\":\"47,750\",\"BuyValue\":47750000.0000,\"Sell\":\"48,550\",\"SellValue\":48550000.0000,\"BuyDiffer\":null,\"BuyDifferValue\":0,\"SellDiffer\":null,\"SellDifferValue\":0,\"GroupDate\":\"\\/Date(1586883600000)\\/\"},{\"Id\":0,\"TypeName\":\"Vàng SJC 1L, 10L, 1KG\",\"BranchName\":\"Hồ Chí Minh\",\"Buy\":\"47,750\",\"BuyValue\":47750000.0000,\"Sell\":\"48,550\",\"SellValue\":48550000.0000,\"BuyDiffer\":null,\"BuyDifferValue\":0,\"SellDiffer\":null,\"SellDifferValue\":0,\"GroupDate\":\"\\/Date(1586889497000)\\/\"},{\"Id\":0,\"TypeName\":\"Vàng SJC 1L, 10L, 1KG\",\"BranchName\":\"Hồ Chí Minh\",\"Buy\":\"47,700\",\"BuyValue\":47700000.0000,\"Sell\":\"48,500\",\"SellValue\":48500000.0000,\"BuyDiffer\":null,\"BuyDifferValue\":0,\"SellDiffer\":null,\"SellDifferValue\":0,\"GroupDate\":\"\\/Date(1586892460000)\\/\"},{\"Id\":0,\"TypeName\":\"Vàng SJC 1L, 10L, 1KG\",\"BranchName\":\"Hồ Chí Minh\",\"Buy\":\"47,650\",\"BuyValue\":47650000.0000,\"Sell\":\"48,450\",\"SellValue\":48450000.0000,\"BuyDiffer\":null,\"BuyDifferValue\":0,\"SellDiffer\":null,\"SellDifferValue\":0,\"GroupDate\":\"\\/Date(1586896934000)\\/\"},{\"Id\":0,\"TypeName\":\"Vàng SJC 1L, 10L, 1KG\",\"BranchName\":\"Hồ Chí Minh\",\"Buy\":\"47,600\",\"BuyValue\":47600000.0000,\"Sell\":\"48,400\",\"SellValue\":48400000.0000,\"BuyDiffer\":null,\"BuyDifferValue\":0,\"SellDiffer\":null,\"SellDifferValue\":0,\"GroupDate\":\"\\/Date(1586909743000)\\/\"},{\"Id\":0,\"TypeName\":\"Vàng SJC 1L, 10L, 1KG\",\"BranchName\":\"Hồ Chí Minh\",\"Buy\":\"47,550\",\"BuyValue\":47550000.0000,\"Sell\":\"48,350\",\"SellValue\":48350000.0000,\"BuyDiffer\":null,\"BuyDifferValue\":0,\"SellDiffer\":null,\"SellDifferValue\":0,\"GroupDate\":\"\\/Date(1586910801000)\\/\"},{\"Id\":0,\"TypeName\":\"Vàng SJC 1L, 10L, 1KG\",\"BranchName\":\"Hồ Chí Minh\",\"Buy\":\"47,500\",\"BuyValue\":47500000.0000,\"Sell\":\"48,300\",\"SellValue\":48300000.0000,\"BuyDiffer\":null,\"BuyDifferValue\":0,\"SellDiffer\":null,\"SellDifferValue\":0,\"GroupDate\":\"\\/Date(1586911220000)\\/\"}]}",
  "raw_payload_hash": "516ccbcfba01a63d38e43766647bbbb77442130ce8fc83b35d7cd4425a52a1c8",
  "from_cache": false
}