{
  "url": "https://sjc.com.vn/GoldPrice/Services/PriceService.ashx",
  "status": 200,
  "text": "{\"success\":true,\"data\":[{\"Id\":0,\"TypeName\":\"Vàng SJC 1L, 10L, 1KG\",\"BranchName\":\"Hồ Chí Minh\",\"Buy\":\"34,950\",\"BuyValue\":34950000.0000,\"Sell\":\"35,150\",\"SellValue\":35150000.0000,\"BuyDiffer\":null,\"BuyDifferValue\":0,\"SellDiffer\":null,\"SellDifferValue\":0,\"GroupDate\":\"\\/Date(1420304400000)\\/\"}]}",
  "raw_payload_hash": "4a442e6ee753cb9e680b7dfea28f85d956818264262a90725a69b814860e8b1f",
  "from_cache": false
}