{
  "url": "https://sjc.com.vn/GoldPrice/Services/PriceService.ashx",
  "status": 200,
  "text": "{\"success\":true,\"data\":[{\"Id\":0,\"TypeName\":\"Vàng SJC 1L, 10L, 1KG\",\"BranchName\":\"Hồ Chí Minh\",\"Buy\":\"35,890\",\"BuyValue\":35890000.0000,\"Sell\":\"36,010\",\"SellValue\":36010000.0000,\"BuyDiffer\":null,\"BuyDifferValue\":0,\"SellDiffer\":null,\"SellDifferValue\":0,\"GroupDate\":\"\\/Date(1411578000000)\\/\"},{\"Id\":0,\"TypeName\":\"Vàng SJC 1L, 10L, 1KG\",\"BranchName\":\"Hồ Chí Minh\",\"Buy\":\"35,830\",\"BuyValue\":35830000.0000,\"Sell\":\"35,950\",\"SellValue\":35950000.0000,\"BuyDiffer\":null,\"BuyDifferValue\":0,\"SellDiffer\":null,\"SellDifferValue\":0,\"GroupDate\":\"\\/Date(1411582500000)\\/\"},{\"Id\":0,\"TypeName\":\"Vàng SJC 1L, 10L, 1KG\",\"BranchName\":\"Hồ Chí Minh\",\"Buy\":\"35,820\",\"BuyValue\":35820000.0000,\"Sell\":\"35,940\",\"SellValue\":35940000.0000,\"BuyDiffer\":null,\"BuyDifferValue\":0,\"SellDiffer\":null,\"SellDifferValue\":0,\"GroupDate\":\"\\/Date(1411601797000)\\/\"}]}",
  "raw_payload_hash": "70cd6707b6736f4e24bf4f0e512d22de8088c3415e820a099507f78e37e8d23d",
  "from_cache": false
}