{
  "url": "https://sjc.com.vn/GoldPrice/Services/PriceService.ashx",
  "status": 200,
  "text": "{\"success\":true,\"data\":[{\"Id\":0,\"TypeName\":\"Vàng SJC 1L, 10L, 1KG\",\"BranchName\":\"Hồ Chí Minh\",\"Buy\":\"40,060\",\"BuyValue\":40060000.0000,\"Sell\":\"40,160\",\"SellValue\":40160000.0000,\"BuyDiffer\":null,\"BuyDifferValue\":0,\"SellDiffer\":null,\"SellDifferValue\":0,\"GroupDate\":\"\\/Date(1312131600000)\\/\"},{\"Id\":0,\"TypeName\":\"Vàng SJC 1L, 10L, 1KG\",\"BranchName\":\"Hồ Chí Minh\",\"Buy\":\"39,900\",\"BuyValue\":39900000.0000,\"Sell\":\"39,970\",\"SellValue\":39970000.0000,\"BuyDiffer\":null,\"BuyDifferValue\":0,\"SellDiffer\":null,\"SellDifferValue\":0,\"GroupDate\":\"\\/Date(1312135713000)\\/\"},{\"Id\":0,\"TypeName\":\"Vàng SJC 1L, 10L, 1KG\",\"BranchName\":\"Hồ Chí Minh\",\"Buy\":\"39,890\",\"BuyValue\":39890000.0000,\"Sell\":\"39,950\",\"SellValue\":39950000.0000,\"BuyDiffer\":null,\"BuyDifferValue\":0,\"SellDiffer\":null,\"SellDifferValue\":0,\"GroupDate\":\"\\/Date(1312135994000)\\/\"},{\"Id\":0,\"TypeName\":\"Vàng SJC 1L, 10L, 1KG\",\"BranchName\":\"Hồ Chí Minh\",\"Buy\":\"39,870\",\"BuyValue\":39870000.0000,\"Sell\":\"39,950\",\"SellValue\":39950000.0000,\"BuyDiffer\":null,\"BuyDifferValue\":0,\"SellDiffer\":null,\"SellDifferValue\":0,\"GroupDate\":\"\\/Date(1312136813000)\\/\"},{\"Id\":0,\"TypeName\":\"Vàng SJC 1L, 10L, 1KG\",\"BranchName\":\"Hồ Chí Minh\",\"Buy\":\"39,870\",\"BuyValue\":39870000.0000,\"Sell\":\"39,940\",\"SellValue\":39940000.0000,\"BuyDiffer\":null,\"BuyDifferValue\":0,\"SellDiffer\":null,\"SellDifferValue\":0,\"GroupDate\":\"\\/Date(1312137845000)\\/\"},{\"Id\":0,\"TypeName\":\"Vàng SJC 1L, 10L, 1KG\",\"BranchName\":\"Hồ Chí Minh\",\"Buy\":\"39,850\",\"BuyValue\":39850000.0000,\"Sell\":\"39,920\",\"SellValue\":39920000.0000,\"BuyDiffer\":null,\"BuyDifferValue\":0,\"SellDiffer\":null,\"SellDifferValue\":0,\"GroupDate\":\"\\/Date(1312139893000)\\/\"},{\"Id\":0,\"TypeName\":\"Vàng SJC 1L, 10L, 1KG\",\"BranchName\":\"Hồ Chí Minh\",\"Buy\":\"39,840\",\"BuyValue\":39840000.0000,\"Sell\":\"39,910\",\"SellValue\":39910000.0000,\"BuyDiffer\":null,\"BuyDifferValue\":0,\"SellDiffer\":null,\"SellDifferValue\":0,\"GroupDate\":\"\\/Date(1312140321000)\\/\"},{\"Id\":0,\"TypeName\":\"Vàng SJC 1L, 10L, 1KG\",\"BranchName\":\"Hồ Chí Minh\",\"Buy\":\"39,830\",\"BuyValue\":39830000.0000,\"Sell\":\"39,900\",\"SellValue\":39900000.0000,\"BuyDiffer\":null,\"BuyDifferValue\":0,\"SellDiffer\":null,\"SellDifferValue\":0,\"GroupDate\":\"\\/Date(1312141233000)\\/\"},{\"Id\":0,\"TypeName\":\"Vàng SJC 1L, 10L, 1KG\",\"BranchName\":\"Hồ Chí Minh\",\"Buy\":\"39,820\",\"BuyValue\":39820000.0000,\"Sell\":\"39,890\",\"SellValue\":39890000.0000,\"BuyDiffer\":null,\"BuyDifferValue\":0,\"SellDiffer\":null,\"SellDifferValue\":0,\"GroupDate\":\"\\/Date(1312141555000)\\/\"},{\"Id\":0,\"TypeName\":\"Vàng SJC 1L, 10L, 1KG\",\"BranchName\":\"Hồ Chí Minh\",\"Buy\":\"39,830\",\"BuyValue\":39830000.0000,\"Sell\":\"39,900\",\"SellValue\":39900000.0000,\"BuyDiffer\":null,\"BuyDifferValue\":0,\"SellDiffer\":null,\"SellDifferValue\":0,\"GroupDate\":\"\\/Date(1312144167000)\\/\"},{\"Id\":0,\"TypeName\":\"Vàng SJC 1L, 10L, 1KG\",\"BranchName\":\"Hồ Chí Minh\",\"Buy\":\"39,850\",\"BuyValue\":39850000.0000,\"Sell\":\"39,910\",\"SellValue\":39910000.0000,\"BuyDiffer\":null,\"BuyDifferValue\":0,\"SellDiffer\":null,\"SellDifferValue\":0,\"GroupDate\":\"\\/Date(1312147765000)\\/\"},{\"Id\":0,\"TypeName\":\"Vàng SJC 1L, 10L, 1KG\",\"BranchName\":\"Hồ Chí Minh\",\"Buy\":\"39,840\",\"BuyValue\":39840000.0000,\"Sell\":\"39,910\",\"SellValue\":39910000.0000,\"BuyDiffer\":null,\"BuyDifferValue\":0,\"SellDiffer\":null,\"SellDifferValue\":0,\"GroupDate\":\"\\/Date(1312155149000)\\/\"},{\"Id\":0,\"TypeName\":\"Vàng SJC 1L, 10L, 1KG\",\"BranchName\":\"Hồ Chí Minh\",\"Buy\":\"39,850\",\"BuyValue\":39850000.0000,\"Sell\":\"39,910\",\"SellValue\":39910000.0000,\"BuyDiffer\":null,\"BuyDifferValue\":0,\"SellDiffer\":null,\"SellDifferValue\":0,\"GroupDate\":\"\\/Date(1312155975000)\\/\"},{\"Id\":0,\"TypeName\":\"Vàng SJC 1L, 10L, 1KG\",\"BranchName\":\"Hồ Chí Minh\",\"Buy\":\"39,850\",\"BuyValue\":39850000.0000,\"Sell\":\"39,920\",\"SellValue\":39920000.0000,\"BuyDiffer\":null,\"BuyDifferValue\":0,\"SellDiffer\":null,\"SellDifferValue\":0,\"GroupDate\":\"\\/Date(1312159451000)\\/\"},{\"Id\":0,\"TypeName\":\"Vàng SJC 1L, 10L, 1KG\",\"BranchName\":\"Hồ Chí Minh\",\"Buy\":\"39,860\",\"BuyValue\":39860000.0000,\"Sell\":\"39,930\",\"SellValue\":39930000.0000,\"BuyDiffer\":null,\"BuyDifferValue\":0,\"SellDiffer\":null,\"SellDifferValue\":0,\"GroupDate\":\"\\/Date(1312161287000)\\/\"},{\"Id\":0,\"TypeName\":\"Vàng SJC 1L, 10L, 1KG\",\"BranchName\":\"Hồ Chí Minh\",\"Buy\":\"39,870\",\"BuyValue\":39870000.0000,\"Sell\":\"39,940\",\"SellValue\":39940000.0000,\"BuyDiffer\":null,\"BuyDifferValue\":0,\"SellDiffer\":null,\"SellDifferValue\":0,\"GroupDate\":\"\\/Date(1312162431000)\\/\"},{\"Id\":0,\"TypeName\":\"Vàng SJC 1L, 10L, 1KG\",\"BranchName\":\"Hồ Chí Minh\",\"Buy\":\"39,860\",\"BuyValue\":39860000.0000,\"Sell\":\"39,920\",\"SellValue\":39920000.0000,\"BuyDiffer\":null,\"BuyDifferValue\":0,\"SellDiffer\":null,\"SellDifferValue\":0,\"GroupDate\":\"\\/Date(1312166606000)\\/\"}]}",
  "raw_payload_hash": "51abb43ce2caa57e8f7f62eaed61a2dcfb58b7f9af19d396350e0accb63be092",
  "from_cache": false
}